farpy/__init__.py
farpy/app.py
farpy-0.0.1.dist-info/LICENSE
farpy-0.0.1.dist-info/METADATA
farpy-0.0.1.dist-info/WHEEL
farpy-0.0.1.dist-info/entry_points.txt
farpy-0.0.1.dist-info/top_level.txt
farpy-0.0.1.dist-info/RECORD
