Metadata-Version: 2.1
Name: farpy
Version: 0.0.1
Summary: Find and replace strings in files like sed does
Author: Asad Rauf
Author-email: asadrauflashari@gmail.com
Maintainer-email: Asad Rauf <asadrauflashari@gmail.com>
License: MIT License
Project-URL: homepage, https://github.com/rauf-asad/farpy
Classifier: Programming Language :: Python
Requires-Python: >=3.8
License-File: LICENSE
Requires-Dist: click (>=8.1.3)
Requires-Dist: colorama (>=0.4.6)
